Metadata-Version: 2.1
Name: stimula-dev
Version: 1.1.3.dev9
Summary: Toolset library for Simple Table Mapping Language (STML)
Home-page: https://github.com/stmlio/stimula
Author: Romke Jonker
Author-email: romke@stml.io
Classifier: Programming Language :: Python :: 3
Classifier: Operating System :: OS Independent
Requires-Python: >=3.6
License-File: LICENSE
Requires-Dist: pyjwt
Requires-Dist: sqlalchemy
Requires-Dist: pandas >=2.1.3
Requires-Dist: numpy >=1.22.4
Requires-Dist: cryptography >=3.4.8
